pytools/__init__.py
pytools/pytools.py
pytools/modules/__init__.py
pytools/modules/artsigngenerator/__init__.py
pytools/modules/artsigngenerator/artsigngenerator.py
pytools/modules/artsigngenerator/resources/background.jpg
pytools/modules/artsigngenerator/resources/icon.jpg
pytools/modules/arxivhelper/__init__.py
pytools/modules/arxivhelper/arxivhelper.py
pytools/modules/calculator/__init__.py
pytools/modules/calculator/calculator.py
pytools/modules/clock/__init__.py
pytools/modules/clock/clock.py
pytools/modules/computersinger/__init__.py
pytools/modules/computersinger/computersinger.py
pytools/modules/computersinger/resources/icon.ico
pytools/modules/computersinger/resources/musicfiles/小幸运
pytools/modules/computersinger/resources/musicfiles/逍遥叹
pytools/modules/controlpcbyemail/__init__.py
pytools/modules/controlpcbyemail/controlpcbyemail.py
pytools/modules/controlpcbyemail/resources/config.json
pytools/modules/controlpcbyemail/resources/word2cmd.json
pytools/modules/coupletgenerator/__init__.py
pytools/modules/coupletgenerator/coupletgenerator.py
pytools/modules/coupletgenerator/resources/icon.png
pytools/modules/decryptbrowser/__init__.py
pytools/modules/decryptbrowser/decryptbrowser.py
pytools/modules/desktoppet/__init__.py
pytools/modules/desktoppet/desktoppet.py
pytools/modules/desktoppet/resources/bingdwendwen/shime1.png
pytools/modules/desktoppet/resources/bingdwendwen/shime10.png
pytools/modules/desktoppet/resources/bingdwendwen/shime11.png
pytools/modules/desktoppet/resources/bingdwendwen/shime12.png
pytools/modules/desktoppet/resources/bingdwendwen/shime13.png
pytools/modules/desktoppet/resources/bingdwendwen/shime14.png
pytools/modules/desktoppet/resources/bingdwendwen/shime15.png
pytools/modules/desktoppet/resources/bingdwendwen/shime16.png
pytools/modules/desktoppet/resources/bingdwendwen/shime17.png
pytools/modules/desktoppet/resources/bingdwendwen/shime18.png
pytools/modules/desktoppet/resources/bingdwendwen/shime19.png
pikachupytools-0.1.24.dist-info/LICENSE
pikachupytools-0.1.24.dist-info/METADATA
pikachupytools-0.1.24.dist-info/WHEEL
pikachupytools-0.1.24.dist-info/top_level.txt
pikachupytools-0.1.24.dist-info/zip-safe
pikachupytools-0.1.24.dist-info/RECORD
