Metadata-Version: 2.1
Name: pikachupytools
Version: 0.1.24
Summary: Pytools: Some useful tools written by pure python.
Home-page: https://github.com/CharlesPikachu/pytools
Author: Charles
Author-email: charlesblwx@gmail.com
License: Apache License 2.0
Platform: UNKNOWN
Classifier: License :: OSI Approved :: Apache Software License
Classifier: Programming Language :: Python :: 3
Classifier: Intended Audience :: Developers
Classifier: Operating System :: OS Independent
License-File: LICENSE
Requires-Dist: SimpleGUICS2Pygame
Requires-Dist: lxml
Requires-Dist: requests
Requires-Dist: fuzzywuzzy
Requires-Dist: PyQt5
Requires-Dist: qrcode
Requires-Dist: pygame
Requires-Dist: psutil
Requires-Dist: js2py
Requires-Dist: markovify
Requires-Dist: python-Levenshtein
Requires-Dist: id-validator
Requires-Dist: IPy
Requires-Dist: pillow
Requires-Dist: openpyxl
Requires-Dist: click
Requires-Dist: beautifulsoup4
Requires-Dist: pythonping
